gmn_python_api/__init__.py
gmn_python_api/__main__.py
gmn_python_api/data_directory.py
gmn_python_api/data_models/traj_summary_20220304_solrange_344.0-345.0.txt
gmn_python_api/data_models/traj_summary_20220304_solrange_344.0-345.0_one_row.txt
gmn_python_api/gmn_rest_api.py
gmn_python_api/iau_showers.py
gmn_python_api/meteor_trajectory_reader.py
gmn_python_api/meteor_trajectory_schema.py
gmn_python_api/py.typed
gmn_python_api-0.0.13.dist-info/LICENSE
gmn_python_api-0.0.13.dist-info/METADATA
gmn_python_api-0.0.13.dist-info/WHEEL
gmn_python_api-0.0.13.dist-info/entry_points.txt
gmn_python_api-0.0.13.dist-info/RECORD
