Metadata-Version: 2.1
Name: gmn-python-api
Version: 0.0.13
Summary: GMN Python API
Home-page: https://github.com/rickybassom/gmn-python-api
License: MIT
Author: Ricky Bassom
Author-email: rickybas12@gmail.com
Requires-Python: >=3.8,<4.0
Classifier: Development Status :: 1 - Planning
Classifier: License :: OSI Approved :: MIT License
Classifier: Programming Language :: Python :: 3
Classifier: Programming Language :: Python :: 3.8
Classifier: Programming Language :: Python :: 3.9
Classifier: Programming Language :: Python :: 3.10
Classifier: Programming Language :: Python :: 3.11
Classifier: Programming Language :: Python :: 3.12
Requires-Dist: beautifulsoup4 (>=4.10.0,<5.0.0)
Requires-Dist: click (==8.0.4)
Requires-Dist: future (>=0.18.3)
Requires-Dist: numpy (>1.20.3)
Requires-Dist: pandas (>=1.1.0,<=1.3.5)
Requires-Dist: requests (>=2.21.0,<3.0.0)
Requires-Dist: types-requests (>=2.27.8,<3.0.0)
Requires-Dist: werkzeug (>=2.2.3)
Project-URL: Changelog, https://github.com/rickybassom/gmn-python-api/releases
Project-URL: Documentation, https://gmn-python-api.readthedocs.io
Project-URL: Repository, https://github.com/rickybassom/gmn-python-api
